README.rst
ecs_deploy.py
setup.py
ecs_deploy_py.egg-info/PKG-INFO
ecs_deploy_py.egg-info/SOURCES.txt
ecs_deploy_py.egg-info/dependency_links.txt
ecs_deploy_py.egg-info/entry_points.txt
ecs_deploy_py.egg-info/not-zip-safe
ecs_deploy_py.egg-info/requires.txt
ecs_deploy_py.egg-info/top_level.txt
tests/__init__.py
tests/test_script.py