Metadata-Version: 1.0
Name: ecs-deploy-py
Version: 0.1.3
Summary: Python script to instigate an automatic blue/green     deployment using Task Definition and Service entities in Amazon's ECS
Home-page: http://github.com/cuttlesoft/ecs-deploy.py
Author: Cuttlesoft, LLC
Author-email: engineering@cuttlesoft.com
License: MIT
Download-URL: https://github.com/cuttlesoft/ecs-deploy.py/tarball/0.1.3
Platform: any
Classifier: Development Status :: 3 - Alpha
Classifier: Environment :: Web Environment
Classifier: Intended Audience :: Developers
Classifier: License :: OSI Approved :: MIT License
Classifier: Operating System :: OS Independent
Classifier: Programming Language :: Python
Classifier: Topic :: Internet :: WWW/HTTP :: Dynamic Content
Classifier: Topic :: Software Development :: Libraries :: Python Modules
